{
  "variants": {
    "facing=east,lit=false": {
      "model": "avaritia_delight:block/extreme_stove",
      "y": 90
    },
    "facing=east,lit=true": {
      "model": "avaritia_delight:block/extreme_stove_on",
      "y": 90
    },
    "facing=north,lit=false": {
      "model": "avaritia_delight:block/extreme_stove"
    },
    "facing=north,lit=true": {
      "model": "avaritia_delight:block/extreme_stove_on"
    },
    "facing=south,lit=false": {
      "model": "avaritia_delight:block/extreme_stove",
      "y": 180
    },
    "facing=south,lit=true": {
      "model": "avaritia_delight:block/extreme_stove_on",
      "y": 180
    },
    "facing=west,lit=false": {
      "model": "avaritia_delight:block/extreme_stove",
      "y": 270
    },
    "facing=west,lit=true": {
      "model": "avaritia_delight:block/extreme_stove_on",
      "y": 270
    }
  }
}